{"imageListData":{"type":"object","objectId":"imageListSample","backgroundImage":{"contentDescription":null,"smallSourceUrl":null,"largeSourceUrl":null,"sources":[{"url":"https://content.r9cdn.net/rimg/dimg/2d/7e/3650b87f-city-47542-1672d189df1.jpg?width=1200&height=630&crop=true","size":"large"}]},"title":"puerto montt","listItems":[{"primaryText":"Vestimenta chilota","imageSource":"https://qph.cf2.quoracdn.net/main-qimg-4b10828318a43e050bf9f1cb2646a7e8-pjlq"},{"primaryText":"Chamanto","imageSource":"https://upload.wikimedia.org/wikipedia/commons/thumb/5/5c/APEC2004_Chamanto.jpg/250px-APEC2004_Chamanto.jpg"},{"primaryText":"Faldas largas y blusas bordadas","imageSource":"https://i.etsystatic.com/13611972/r/il/baec42/2649633721/il_1080xN.2649633721_jvzl.jpg"}],"logoUrl":"https://cdn-www.bluestacks.com/bs-images/gametiles_com.amazon.dee_.app_22.jpg","hintText":"\"Alexa, ropa típica de puerto montt\""}}